src/__init__.py
src/__main__.py
src/cli.py
src/fetchers/jenkins_fetcher.py
src/ml/__init__.py
src/ml/ai_log_analyzer.py
src/ml/analysis_formatter.py
src/ml/gru_classifier.py
src/ml/hybrid_classifier.py
src/ml/log_analyzer.py
src/ml/models.py
src/ml/root_cause_extractor.py
src/models/__init__.py
src/models/schemas.py
src/parsers/__init__.py
src/parsers/base_parser.py
src/parsers/factory.py
src/parsers/generic_parser.py
src/parsers/github_actions_parser.py
src/parsers/gitlab_parser.py
src/parsers/jenkins_parser.py
src/utils/__init__.py
src/utils/display.py
ai_logguard-1.0.1.dist-info/METADATA
ai_logguard-1.0.1.dist-info/WHEEL
ai_logguard-1.0.1.dist-info/entry_points.txt
ai_logguard-1.0.1.dist-info/top_level.txt
ai_logguard-1.0.1.dist-info/RECORD
