Metadata-Version: 2.4
Name: ai-logguard
Version: 1.0.1
Summary: 🤖 AI-powered CLI for CI/CD log analysis with ML + LLM hybrid intelligence
Home-page: https://github.com/SyLe-Van/AI-LogGuard
Author: Sy Le Van
Author-email: Sy Le Van <syle.dev@gmail.com>
License-Expression: MIT
Project-URL: Homepage, https://github.com/SyLe-Van/AI-LogGuard
Project-URL: Repository, https://github.com/SyLe-Van/AI-LogGuard
Project-URL: Issues, https://github.com/SyLe-Van/AI-LogGuard/issues
Keywords: ci-cd,devops,log-analysis,ai,ml,llm,jenkins,github-actions,gitlab
Classifier: Development Status :: 4 - Beta
Classifier: Intended Audience :: Developers
Classifier: Topic :: Software Development :: Quality Assurance
Classifier: Topic :: Software Development :: Testing
Classifier: Topic :: System :: Monitoring
Classifier: Programming Language :: Python :: 3
Classifier: Programming Language :: Python :: 3.8
Classifier: Programming Language :: Python :: 3.9
Classifier: Programming Language :: Python :: 3.10
Classifier: Programming Language :: Python :: 3.11
Classifier: Programming Language :: Python :: 3.12
Classifier: Programming Language :: Python :: 3.13
Classifier: Operating System :: OS Independent
Classifier: Environment :: Console
Requires-Python: >=3.8
Requires-Dist: typer>=0.15.0
Requires-Dist: rich>=13.7.1
Requires-Dist: requests>=2.31.0
Requires-Dist: pydantic>=2.10.0
Requires-Dist: python-dotenv>=1.0.1
Requires-Dist: torch>=2.0.0
Requires-Dist: numpy>=1.24.0
Requires-Dist: scikit-learn>=1.3.0
Provides-Extra: dev
Requires-Dist: pytest>=8.1.1; extra == "dev"
Requires-Dist: pytest-cov>=5.0.0; extra == "dev"
Requires-Dist: pytest-mock>=3.14.0; extra == "dev"
Requires-Dist: black>=24.3.0; extra == "dev"
Requires-Dist: flake8>=7.0.0; extra == "dev"
Requires-Dist: mypy>=1.9.0; extra == "dev"
Requires-Dist: isort>=5.13.2; extra == "dev"
Provides-Extra: ml
Requires-Dist: scikit-learn>=1.3.0; extra == "ml"
Requires-Dist: numpy>=1.24.0; extra == "ml"
Dynamic: author
Dynamic: home-page
Dynamic: requires-python
